poly_pack/__init__.py
poly_pack/automate.py
poly_pack/data_processing.py
poly_pack/esaxsmask.edf
poly_pack/esaxsnobsmax.edf
poly_pack/fitting.py
poly_pack/graphing.py
poly_pack/maxmask.edf
poly_pack/sample.py
poly_pack/saxsmask.edf
poly_pack/waxsmask.edf
poly_pack-0.25.dist-info/METADATA
poly_pack-0.25.dist-info/WHEEL
poly_pack-0.25.dist-info/top_level.txt
poly_pack-0.25.dist-info/RECORD
